yototec/__init__.py
yototec/client.py
yototec-0.1.1.dist-info/licenses/LICENSE
yototec-0.1.1.dist-info/METADATA
yototec-0.1.1.dist-info/WHEEL
yototec-0.1.1.dist-info/top_level.txt
yototec-0.1.1.dist-info/RECORD
