Metadata-Version: 2.4
Name: yototec
Version: 0.1.1
Summary: A Python client for interacting with the Yototec Market API
Author-email: Edward Chen <rchen@yototec.com>
License: Copyright (c) 2024-2025 Yototec Ltd
Project-URL: Homepage, https://github.com/Yototec/client_lightweight
Project-URL: Source Code, https://github.com/Yototec/client_lightweight
Project-URL: Tracker, https://github.com/Yototec/client_lightweight/issues
Keywords: yototec,api,client
Classifier: Programming Language :: Python :: 3
Classifier: License :: OSI Approved :: MIT License
Classifier: Operating System :: OS Independent
Requires-Python: >=3.7
License-File: LICENSE
Requires-Dist: requests
Dynamic: license-file
